{"stats":{"minecraft:killed_by":{"undead_revamp2:the_moonflower":2,"graveyard:acolyte":10,"minecraft:magma_cube":1,"arphex:spider_moth":3,"minecraft:zombie":38,"born_in_chaos_v1:lifestealer_true_form":2,"arphex:scorpioid_clone":2,"born_in_chaos_v1:mother_spider":3,"minecraft:warden":18,"alexsmobs:tarantula_hawk":1,"minecraft:wither":7,"cave_dweller:cave_dweller":4,"born_in_chaos_v1:dread_hound":2,"arphex:ant_arsonist_worker":1,"minecraft:drowned":5,"arphex:centipede_evictor":1,"born_in_chaos_v1:supreme_bonescaller_stage_2":3,"arphex:scorpioid_bloodluster":3,"born_in_chaos_v1:bone_imp":1,"undead_revamp2:thehorrors":1,"arphex:blood_worm":1,"apollyon:the_damned":2,"undead_revamp2:therod":2,"minecraft:skeleton":9,"born_in_chaos_v1:corpse_fish":1,"alexsmobs:crimson_mosquito":3,"graveyard:corrupted_vindicator":3,"born_in_chaos_v1:nightmare_stalker":18,"minecraft:piglin_brute":3,"born_in_chaos_v1:baby_spider":2,"minecraft:pillager":5,"sons_of_sins:betrayed_guzzler":2,"alexsmobs:grizzly_bear":2,"minecraft:vex":4,"born_in_chaos_v1:baby_skeleton_minion":1,"born_in_chaos_v1:zombie_lumberjack":1,"arphex:spider_jump":2,"arphex:draconic_voidlasher":5,"undead_revamp2:thesomnolence":1,"undead_revamp2:thespitter":1,"minecraft:guardian":1,"arphex:centipede_stalker":1,"minecraft:evoker":1,"undead_revamp2:sucker":3,"minecraft:wither_skeleton":4,"minecraft:creeper":4,"born_in_chaos_v1:glutton_fish":2,"born_in_chaos_v1:corpse_fly":3,"graveyard:skeleton_creeper":2,"undead_revamp2:clogger":2,"man:managgresive":8,"born_in_chaos_v1:krampus_henchman":1,"minecraft:piglin":3,"minecraft:cave_spider":2,"undead_revamp2:theheavy":4,"born_in_chaos_v1:firelight_not_despawn":1,"minecraft:player":9,"minecraft:spider":7,"minecraft:enderman":4,"minecraft:iron_golem":2,"arphex:hornet_harbinger":1},"minecraft:crafted":{"minecraft:black_dye":1,"arphex:spider_jar":2,"minecraft:blaze_powder":22,"minecraft:birch_boat":11,"born_in_chaos_v1:spiny_shell_armor_chestplate":1,"minecraft:music_disc_11":1,"born_in_chaos_v1:nightmare_mantleofthe_night_chestplate":1,"minecraft:diamond_helmet":2,"minecraft:beacon":1,"arphex:scorch_charge":5,"minecraft:iron_door":3,"minecraft:jungle_boat":3,"minecraft:smithing_table":1,"born_in_chaos_v1:bonescaller_staff":1,"minecraft:fletching_table":1,"born_in_chaos_v1:staff_of_magic_arrows":1,"comforts:sleeping_bag_black":1,"minecraft:wooden_hoe":1,"minecraft:golden_leggings":1,"minecraft:iron_pickaxe":39,"minecraft:netherite_ingot":11,"minecraft:golden_carrot":149,"vtaw_mw:diamond_battleaxe":1,"minecraft:spruce_fence":6,"born_in_chaos_v1:smoked_monster_flesh":8,"born_in_chaos_v1:spiny_shell_armor_helmet":1,"arphex:infernal_helmet":1,"minecraft:stone_pickaxe":37,"arphex:mangled_scorpion_flesh":8,"minecraft:spruce_boat":8,"minecraft:lead":2,"biomesoplenty:jacaranda_boat":3,"minecraft:enchanting_table":1,"biomesoplenty:redwood_planks":76,"arphex:black_widow_bow":5,"minecraft:leather_helmet":1,"minecraft:enchanted_book":11,"born_in_chaos_v1:dark_metal_nugget":133,"minecraft:oak_chest_boat":6,"minecraft:fermented_spider_eye":80,"minecraft:iron_shovel":20,"arphex:mangled_spider_flesh":13,"minecraft:soul_sand":11,"minecraft:cobblestone_slab":138,"arphex:infernal_leggings":1,"minecraft:lightning_rod":1,"minecraft:stone":33,"born_in_chaos_v1:dark_metal_ingot":45,"arphex:infernal_boots":1,"securitycraft:laser_block":1,"minecraft:stone_brick_slab":30,"born_in_chaos_v1:dark_ritual_dagger":1,"minecraft:bow":11,"minecraft:chest":40,"minecraft:netherite_helmet":1,"minecraft:ender_eye":25,"minecraft:stone_bricks":16,"minecraft:oak_fence":3,"arphex:abyssal_annihilator":1,"born_in_chaos_v1:pileof_dark_metal":25,"minecraft:golden_boots":1,"vtaw_mw:diamond_katana":2,"biomesoplenty:jacaranda_planks":84,"minecraft:cauldron":1,"minecraft:iron_helmet":26,"minecraft:spruce_chest_boat":3,"minecraft:stick":636,"arphex:infernal_shard":4,"minecraft:iron_ingot":881,"biomesoplenty:mahogany_boat":2,"securitycraft:universal_block_reinforcer_lvl1":1,"minecraft:oak_door":36,"minecraft:tripwire_hook":2,"born_in_chaos_v1:darkwarblade":1,"born_in_chaos_v1:nightmare_mantleofthe_night_leggings":1,"minecraft:spruce_button":11,"born_in_chaos_v1:nightmare_mantleofthe_night_boots":1,"graveyard:dark_iron_ingot":64,"minecraft:furnace":10,"minecraft:blast_furnace":1,"born_in_chaos_v1:nightmare_mantleofthe_night_helmet":1,"minecraft:flint_and_steel":2,"born_in_chaos_v1:intoxicating_dagger":1,"minecraft:netherite_chestplate":1,"born_in_chaos_v1:bone_handle":6,"backpacked:backpack":3,"minecraft:birch_sign":3,"biomesoplenty:umbran_planks":416,"minecraft:music_disc_mellohi":1,"minecraft:iron_sword":7,"minecraft:cooked_salmon":18,"minecraft:mangrove_planks":20,"born_in_chaos_v1:bone_heart":2,"minecraft:jungle_planks":40,"minecraft:torch":916,"minecraft:diamond_chestplate":4,"minecraft:ender_chest":1,"minecraft:smooth_stone":5,"born_in_chaos_v1:dark_metal_block":2,"minecraft:birch_slab":6,"minecraft:slime_block":1,"arphex:silk_slinger":1,"minecraft:bookshelf":19,"minecraft:cooked_mutton":24,"minecraft:quartz_block":22,"minecraft:glass":3,"minecraft:diamond_leggings":2,"minecraft:netherite_boots":1,"arphex:formic_fireblaster":2,"minecraft:birch_door":15,"born_in_chaos_v1:soul_cutlass":1,"minecraft:cooked_rabbit":1,"minecraft:glass_bottle":18,"minecraft:deepslate":3,"minecraft:emerald":284,"minecraft:cooked_porkchop":31,"minecraft:spruce_door":9,"minecraft:copper_ingot":152,"born_in_chaos_v1:smoked_flesh":475,"minecraft:gold_ingot":709,"minecraft:birch_stairs":120,"minecraft:packed_ice":1,"comforts:sleeping_bag_white":2,"arphex:infernal_chestplate":1,"arphex:mantle_of_vitality":1,"minecraft:bone_meal":301,"born_in_chaos_v1:pieceofdarkmetal":9,"minecraft:diamond":21,"minecraft:ladder":75,"securitycraft:universal_block_remover":1,"minecraft:spruce_slab":12,"minecraft:diamond_boots":4,"minecraft:redstone_block":2,"minecraft:dark_oak_planks":366,"minecraft:coal_block":16,"minecraft:crossbow":3,"securitycraft:universal_block_modifier":2,"arphex:weather_sensor":1,"minecraft:conduit":1,"minecraft:golden_apple":27,"minecraft:wooden_axe":4,"minecraft:oak_stairs":104,"minecraft:iron_leggings":27,"minecraft:white_bed":89,"graveyard:dark_iron_block":9,"undead_revamp2:chainsword":1,"minecraft:oak_planks":1024,"minecraft:dark_oak_boat":7,"minecraft:mangrove_boat":1,"minecraft:cobblestone_stairs":68,"dixtas_armory:diamond_battle_axe":1,"arphex:infernal_ingot":4,"nethersdelight:hoglin_sirloin":15,"minecraft:dark_oak_door":36,"minecraft:hopper":2,"dixtas_armory:diamond_longsword":1,"minecraft:iron_boots":29,"minecraft:netherite_upgrade_smithing_template":14,"minecraft:chiseled_stone_bricks":15,"born_in_chaos_v1:shattered_skull":4,"minecraft:smoker":2,"minecraft:oak_slab":12,"arphex:bane_of_the_darkness":3,"born_in_chaos_v1:smoked_fish":6,"minecraft:crafting_table":64,"minecraft:spruce_planks":400,"minecraft:wooden_pickaxe":5,"securitycraft:universal_owner_changer":1,"minecraft:birch_planks":1280,"born_in_chaos_v1:spider_bite_sword":1,"biomesoplenty:fir_planks":476,"minecraft:shield":36,"minecraft:diamond_pickaxe":3,"minecraft:iron_chestplate":35,"born_in_chaos_v1:spiritual_dust":180,"minecraft:stone_sword":4,"minecraft:snow_block":38,"minecraft:cherry_planks":4,"minecraft:wooden_sword":3,"minecraft:raw_iron":9,"minecraft:coal":171,"biomesoplenty:mahogany_planks":40,"dropthemeat:cooked_villager":1,"arphex:mangled_fly_flesh":5,"minecraft:netherite_leggings":1,"minecraft:rabbit_hide":17,"minecraft:iron_axe":13,"born_in_chaos_v1:fried_maggot":13,"minecraft:birch_chest_boat":2,"minecraft:iron_hoe":1,"minecraft:slime_ball":27,"minecraft:netherite_scrap":40,"alexsmobs:flying_fish_boots":2,"minecraft:cooked_beef":100,"minecraft:sugar":116,"minecraft:cooked_cod":3,"minecraft:bone_block":9,"minecraft:crimson_planks":56,"minecraft:dark_oak_stairs":24,"minecraft:bucket":2,"vtaw_mw:iron_longsword":3,"minecraft:stone_axe":7,"minecraft:lodestone":1,"minecraft:air":0,"minecraft:bread":14,"born_in_chaos_v1:shell_mace":1,"minecraft:oak_boat":12,"minecraft:white_wool":11,"minecraft:gold_nugget":1211,"vtaw_mw:iron_katana":3,"minecraft:acacia_planks":12,"undead_revamp2:bostroxingot":26,"minecraft:end_crystal":3,"minecraft:lapis_lazuli":9,"minecraft:lapis_block":6},"minecraft:used":{"minecraft:moss_block":3,"minecraft:jack_o_lantern":2,"minecraft:writable_book":4,"minecraft:chiseled_deepslate":3,"minecraft:stone":22,"minecraft:red_nether_brick_stairs":1,"minecraft:rotten_flesh":24,"minecraft:soul_sand":24,"minecraft:cracked_deepslate_tiles":3,"minecraft:snowball":20,"minecraft:spruce_boat":18,"minecraft:lava_bucket":3,"horror_element_mod:villager_head":3,"minecraft:dark_oak_slab":3,"minecraft:netherite_boots":1,"minecraft:bow":6881,"minecraft:oak_sapling":3,"minecraft:cooked_cod":606,"biomesoplenty:flesh":1,"minecraft:mossy_stone_bricks":4,"minecraft:leather_leggings":1,"minecraft:damaged_anvil":2,"minecraft:blackstone":38,"minecraft:leather_chestplate":2,"minecraft:wooden_pickaxe":189,"minecraft:mossy_stone_brick_stairs":3,"minecraft:jungle_boat":3,"minecraft:golden_apple":36,"minecraft:blast_furnace":1,"biomesoplenty:jacaranda_planks":17,"alexsmobs:leafcutter_anthill":1,"vtaw_mw:iron_longsword":514,"minecraft:birch_fence":4,"dropthemeat:cooked_wolf":2,"minecraft:birch_slab":13,"biomesoplenty:yellow_autumn_sapling":1,"minecraft:nether_wart_block":25,"minecraft:diamond_sword":3378,"sons_of_sins:flesh_of_demise":1,"minecraft:smithing_table":1,"minecraft:birch_log":20,"minecraft:oak_boat":8,"minecraft:enchanting_table":1,"minecraft:armor_stand":1,"born_in_chaos_v1:darkwarblade":21,"minecraft:cooked_salmon":86,"minecraft:torch":870,"minecraft:brewing_stand":1,"minecraft:cod_bucket":11,"dropthemeat:cooked_squid":9,"minecraft:chipped_anvil":4,"minecraft:muddy_mangrove_roots":2,"born_in_chaos_v1:nightmare_mantleofthe_night_leggings":1,"dropthemeat:cooked_villager":3,"born_in_chaos_v1:intoxicating_dagger":47,"minecraft:barrel":7,"minecraft:diamond_chestplate":1,"minecraft:basalt":93,"comforts:sleeping_bag_white":122,"farmersdelight:tomato_seeds":7,"minecraft:acacia_planks":7,"minecraft:wheat_seeds":65,"minecraft:birch_planks":100,"minecraft:lead":1,"minecraft:spruce_chest_boat":8,"minecraft:cauldron":1,"vtaw_mw:diamond_katana":110,"minecraft:leather_boots":1,"minecraft:spruce_fence_gate":1,"minecraft:red_bed":9,"minecraft:white_bed":152,"minecraft:spruce_log":2,"arphex:mangled_scorpion_flesh":6,"minecraft:diamond_pickaxe":7384,"minecraft:diamond_shovel":573,"minecraft:potion":5,"minecraft:purple_bed":28,"minecraft:cooked_porkchop":21,"vtaw_mw:iron_katana":421,"minecraft:red_sand":17,"minecraft:bone_block":1,"minecraft:polished_basalt":3,"dixtas_armory:diamond_battle_axe":14,"dropthemeat:cooked_bee":5,"minecraft:obsidian":42,"arphex:ascendant_staff":23,"minecraft:item_frame":1,"minecraft:golden_sword":44,"minecraft:deepslate_diamond_ore":5,"minecraft:written_book":2,"minecraft:skeleton_skull":1,"minecraft:diamond_boots":1,"minecraft:wither_skeleton_skull":4,"minecraft:stone_pickaxe":2353,"minecraft:oak_planks":207,"minecraft:sandstone":47,"minecraft:chainmail_helmet":1,"minecraft:diamond_axe":66,"minecraft:sugar_cane":15,"minecraft:white_wool":11,"minecraft:netherite_leggings":2,"minecraft:crossbow":25,"alexsmobs:terrapin_bucket":1,"minecraft:black_terracotta":3,"minecraft:lever":3,"minecraft:dark_oak_log":1,"minecraft:bread":78,"graveyard:fire_brazier":2,"undead_revamp2:chainsword":2470,"arphex:ant_nest":1,"nethersdelight:hoglin_sirloin":20,"alexsmobs:cooked_moose_ribs":15,"born_in_chaos_v1:mesh_door":1,"minecraft:cooked_rabbit":4,"minecraft:coarse_dirt":33,"minecraft:rose_bush":2,"minecraft:flint_and_steel":71,"undead_revamp2:blacpetalblock":1,"minecraft:ender_chest":2,"farmersdelight:rich_soil":3,"minecraft:stone_hoe":49,"minecraft:cooked_chicken":23,"minecraft:dirt":437,"alexsmobs:cooked_kangaroo_meat":1,"minecraft:spruce_fence":20,"minecraft:iron_hoe":14,"minecraft:wooden_axe":62,"born_in_chaos_v1:nightmare_mantleofthe_night_helmet":1,"minecraft:oak_stairs":110,"minecraft:iron_boots":4,"minecraft:cooked_beef":64,"minecraft:pumpkin":10,"minecraft:iron_leggings":6,"vtaw_mw:diamond_battleaxe":11,"born_in_chaos_v1:trident_hayfork":47,"graveyard:light_gray_urn":2,"minecraft:cobblestone_stairs":2,"comforts:sleeping_bag_black":10,"minecraft:baked_potato":5,"minecraft:birch_boat":20,"minecraft:wooden_hoe":10,"minecraft:stone_axe":283,"minecraft:pumpkin_pie":12,"minecraft:wither_rose":5,"minecraft:birch_stairs":54,"born_in_chaos_v1:bonescaller_staff":12,"minecraft:spruce_slab":25,"minecraft:polished_blackstone":17,"minecraft:ladder":27,"minecraft:chest":33,"born_in_chaos_v1:nightmare_mantleofthe_night_chestplate":1,"born_in_chaos_v1:soul_cutlass":16,"born_in_chaos_v1:smoked_flesh":940,"minecraft:grass_block":28,"dropthemeat:cooked_fox":1,"minecraft:dark_oak_boat":16,"minecraft:furnace":9,"minecraft:egg":41,"minecraft:potato":15,"born_in_chaos_v1:nightmare_mantleofthe_night_boots":1,"minecraft:spruce_door":6,"arphex:mangled_spider_flesh":4,"minecraft:cookie":4,"minecraft:sand":144,"minecraft:netherite_helmet":1,"minecraft:pumpkin_seeds":1,"minecraft:crying_obsidian":2,"minecraft:lectern":20,"biomesoplenty:jacaranda_boat":3,"minecraft:diamond_ore":1,"minecraft:lilac":3,"minecraft:polished_andesite_slab":4,"minecraft:wooden_sword":84,"arphex:mangled_fly_flesh":5,"minecraft:dark_oak_fence":1,"alexsmobs:leafcutter_ant_chamber":1,"born_in_chaos_v1:dark_ritual_dagger":3,"minecraft:stone_sword":340,"born_in_chaos_v1:smoked_fish":175,"born_in_chaos_v1:fried_maggot":7,"minecraft:netherrack":1982,"minecraft:anvil":5,"minecraft:stone_stairs":5,"minecraft:birch_chest_boat":14,"minecraft:iron_axe":1466,"minecraft:melon_seeds":2,"undead_revamp2:huntereye":4,"minecraft:smooth_basalt":15,"minecraft:cobbled_deepslate":650,"alexsdelight:cooked_bison":6,"minecraft:water_bucket":13,"minecraft:fletching_table":1,"minecraft:gilded_blackstone":1,"biomesoplenty:mahogany_log":1,"minecraft:polished_blackstone_bricks":119,"minecraft:mossy_cobblestone":2,"minecraft:tnt":14,"minecraft:oak_slab":41,"minecraft:crafting_table":71,"minecraft:birch_sign":7,"minecraft:cod":5,"minecraft:oak_log":4,"minecraft:mud":19,"minecraft:ender_eye":26,"minecraft:iron_pickaxe":4459,"biomesoplenty:mahogany_boat":2,"minecraft:cobblestone":758,"refurbished_furniture:oak_drawer":1,"minecraft:dark_oak_chest_boat":5,"minecraft:iron_shovel":1942,"minecraft:oak_sign":1,"minecraft:shield":1214,"minecraft:iron_sword":1216,"minecraft:iron_chestplate":2,"minecraft:carrot":29,"minecraft:tuff":1,"minecraft:milk_bucket":1,"dropthemeat:cooked_piglin_porkchop":17,"minecraft:iron_helmet":5,"minecraft:stone_bricks":23,"farmersdelight:cutting_board":1,"minecraft:magma_block":1,"minecraft:scaffolding":5,"minecraft:hay_block":2,"minecraft:gray_bed":1,"minecraft:beetroot_seeds":1,"minecraft:oak_chest_boat":15,"minecraft:dark_oak_stairs":28,"minecraft:ender_pearl":2,"biomesoplenty:fir_planks":90,"minecraft:blue_bed":33,"minecraft:note_block":1,"minecraft:melon_slice":2,"minecraft:cyan_bed":22,"minecraft:string":2,"born_in_chaos_v1:smoked_monster_flesh":1,"minecraft:gravel":118,"arphex:maggot_grub":1,"minecraft:andesite":8,"dixtas_armory:diamond_longsword":1029,"minecraft:golden_pickaxe":49,"minecraft:experience_bottle":7,"minecraft:cobweb":7,"minecraft:oak_fence":3,"minecraft:stone_shovel":96,"biomesoplenty:redwood_planks":19,"minecraft:spruce_planks":186,"born_in_chaos_v1:shell_mace":2,"minecraft:oak_door":38,"minecraft:spyglass":1,"minecraft:hopper":19,"minecraft:spruce_stairs":1,"minecraft:diamond_helmet":1,"minecraft:raw_iron_block":1,"minecraft:salmon_bucket":6,"minecraft:birch_door":6,"minecraft:stone_brick_slab":6,"minecraft:dark_oak_planks":69,"biomesoplenty:orange_sand":1,"minecraft:crimson_planks":37,"minecraft:golden_carrot":32,"alexsmobs:lobster_bucket":2,"minecraft:mangrove_boat":1,"minecraft:cooked_mutton":19,"minecraft:iron_ore":4,"minecraft:glass_bottle":24,"minecraft:netherite_chestplate":1,"minecraft:andesite_slab":1,"minecraft:cobblestone_slab":23,"minecraft:terracotta":3,"dropthemeat:cooked_bat":2,"minecraft:dark_oak_door":21,"minecraft:smoker":4,"minecraft:cracked_polished_blackstone_bricks":52,"minecraft:map":5,"minecraft:fishing_rod":458,"minecraft:bucket":32,"born_in_chaos_v1:wood_splitter_axe":33,"biomesoplenty:umbran_boat":2},"minecraft:custom":{"minecraft:interact_with_crafting_table":789,"minecraft:damage_blocked_by_shield":48630,"minecraft:play_time":10326360,"minecraft:deaths":308,"minecraft:jump":84953,"minecraft:interact_with_cartography_table":9,"minecraft:interact_with_smoker":180,"minecraft:inspect_dispenser":13,"minecraft:horse_one_cm":5236850,"minecraft:inspect_dropper":3,"minecraft:interact_with_anvil":151,"minecraft:inspect_hopper":93,"minecraft:tune_noteblock":17,"minecraft:time_since_rest":16375,"minecraft:swim_one_cm":2466145,"minecraft:open_chest":8148,"minecraft:damage_resisted":145,"minecraft:play_noteblock":2,"minecraft:talked_to_villager":167,"minecraft:interact_with_brewingstand":36,"minecraft:fill_cauldron":1,"minecraft:interact_with_campfire":101,"minecraft:damage_dealt_resisted":76303,"minecraft:raid_win":2,"minecraft:boat_one_cm":19080234,"minecraft:damage_taken":170906,"minecraft:open_barrel":591,"minecraft:bell_ring":7,"minecraft:eat_cake_slice":16,"minecraft:leave_game":151,"minecraft:time_since_death":16319,"minecraft:enchant_item":38,"minecraft:interact_with_furnace":235,"minecraft:traded_with_villager":28,"minecraft:sleep_in_bed":433,"minecraft:damage_dealt":406525,"minecraft:interact_with_smithing_table":28,"minecraft:sneak_time":259091,"minecraft:interact_with_lectern":12,"minecraft:interact_with_blast_furnace":252,"minecraft:total_world_time":10326360,"minecraft:interact_with_stonecutter":5,"minecraft:fly_one_cm":5108158,"minecraft:fish_caught":306,"minecraft:fall_one_cm":1004016,"minecraft:animals_bred":27,"minecraft:sprint_one_cm":13487796,"minecraft:drop":3399,"minecraft:walk_on_water_one_cm":1421066,"minecraft:interact_with_loom":4,"minecraft:open_enderchest":42,"minecraft:player_kills":19,"minecraft:crouch_one_cm":549406,"minecraft:mob_kills":7488,"minecraft:climb_one_cm":1163718,"minecraft:walk_one_cm":36002227,"minecraft:walk_under_water_one_cm":1364837,"minecraft:raid_trigger":1,"minecraft:interact_with_grindstone":32,"minecraft:damage_absorbed":1404,"minecraft:trigger_trapped_chest":12},"minecraft:killed":{"arphex:small_web":8,"born_in_chaos_v1:mr_pumpkin":11,"born_in_chaos_v1:zombie_lumberjack":11,"born_in_chaos_v1:skeleton_demoman":16,"arphex:long_legs_tiny":4,"minecraft:cod":8,"minecraft:zombie_horse":1,"undead_revamp2:theswarmer":19,"undead_revamp2:deadclogger":1,"graveyard:acolyte":32,"alexsmobs:leafcutter_ant":17,"arphex:spider_lurker":2,"alexsmobs:straddler":23,"alexsmobs:centipede_head":3,"arphex:ant_arsonist":39,"undead_revamp2:thepregnant":7,"minecraft:skeleton_horse":7,"minecraft:tropical_fish":1,"undead_revamp2:thespitter":15,"arphex:spider_moth_larvae":5,"arphex:spider_larvae_tiny":216,"minecraft:salmon":4,"born_in_chaos_v1:bone_imp":6,"minecraft:iron_golem":6,"undead_revamp2:theheavy":5,"minecraft:pillager":156,"minecraft:goat":2,"minecraft:zombie":933,"alexsmobs:cachalot_whale":4,"minecraft:evoker":2,"undead_revamp2:theimmortal":7,"graveyard:corrupted_vindicator":19,"arphex:silverfish_spectre":18,"minecraft:vindicator":10,"arphex:beetle_bulwark":4,"born_in_chaos_v1:skeleton_thrasher_not_despawn":1,"undead_revamp2:bomber":30,"arphex:beetle_tick_mite":1,"born_in_chaos_v1:firelight":19,"arphex:scorpion_larvae":10,"minecraft:warden":1,"minecraft:husk":12,"graveyard:ghoul":13,"minecraft:ravager":2,"alexsmobs:rhinoceros":1,"born_in_chaos_v1:krampus_henchman":4,"born_in_chaos_v1:bloody_gadfly":4,"undead_revamp2:thesomnolence":33,"alexsmobs:crocodile":5,"alexsmobs:elephant":2,"born_in_chaos_v1:controlled_baby_skeleton":4,"arphex:spider_goliath":1,"arphex:giant_web":6,"minecraft:zombified_piglin":24,"minecraft:witch":19,"minecraft:spider":276,"arphex:teleport_ghost":9,"arphex:roach_riverspawn":23,"arphex:ant_arsonist_worker":30,"alexsmobs:alligator_snapping_turtle":1,"minecraft:bee":14,"undead_revamp2:therod":10,"minecraft:piglin_brute":9,"born_in_chaos_v1:firelight_not_despawn":7,"arphex:butterfly_bewitcher":34,"minecraft:piglin":29,"born_in_chaos_v1:bonescaller":17,"alexsmobs:grizzly_bear":7,"minecraft:zombie_villager":22,"born_in_chaos_v1:glutton_fish":18,"alexsmobs:stradpole":9,"undead_revamp2:thebeartamer":11,"alexsmobs:crimson_mosquito":26,"minecraft:sheep":21,"undead_revamp2:theordure":3,"undead_revamp2:thebidyupside":26,"born_in_chaos_v1:zombie_fisherman":11,"alexsmobs:terrapin":3,"alexsmobs:toucan":3,"minecraft:ghast":28,"cave_dweller:cave_dweller":8,"graveyard:corrupted_pillager":15,"born_in_chaos_v1:siamese_skeletonsleft":32,"alexsmobs:bone_serpent":2,"arphex:hornet_harbinger_giant":1,"minecraft:vex":8,"arphex:spider_brood":11,"undead_revamp2:thegliter":6,"alexsmobs:tasmanian_devil":2,"minecraft:slime":12,"born_in_chaos_v1:zombie_bruiser":20,"alexsmobs:blue_jay":2,"arphex:blood_worm":36,"arphex:centipede_stalker":15,"minecraft:drowned":70,"born_in_chaos_v1:corpse_fish":63,"born_in_chaos_v1:baby_skeleton":28,"born_in_chaos_v1:swarmer":22,"born_in_chaos_v1:spirit_guide_assistant":1,"minecraft:hoglin":21,"alexsmobs:emu":6,"born_in_chaos_v1:decaying_zombie":31,"alexsmobs:cockroach":7,"alexsmobs:gazelle":6,"alexsmobs:moose":11,"arphex:spider_prowler":1,"minecraft:wither_skeleton":62,"minecraft:villager":8,"arphex:scorpioid_bloodluster":3,"arphex:spider_moth":5,"arphex:mosquito_morbidity":5,"minecraft:cave_spider":19,"alexsmobs:lobster":1,"arphex:spider_flat":13,"born_in_chaos_v1:restless_spirit":27,"born_in_chaos_v1:door_knight_not_despawn":1,"undead_revamp2:clogger":1,"undead_revamp2:axestrom":35,"alexsmobs:murmur":1,"minecraft:dolphin":1,"graveyard:wraith":22,"born_in_chaos_v1:siamese_skeletonsright":34,"born_in_chaos_v1:baby_skeleton_minion":20,"minecraft:skeleton":701,"minecraft:fox":1,"alexsmobs:capuchin_monkey":2,"minecraft:chicken":37,"born_in_chaos_v1:skeleton_thrasher":14,"alexsmobs:skelewag":4,"born_in_chaos_v1:supreme_bonescaller_stage_2":3,"minecraft:cat":2,"minecraft:magma_cube":129,"arphex:long_legs":5,"alexsmobs:seal":30,"born_in_chaos_v1:dread_hound_not_despawn":3,"arphex:centipede_evictor_larvae":22,"alexsmobs:maned_wolf":1,"born_in_chaos_v1:corpse_fly":143,"alexsmobs:rain_frog":2,"alexsmobs:roadrunner":4,"arphex:spider_larvae":83,"born_in_chaos_v1:door_knight":35,"minecraft:cow":57,"undead_revamp2:thehunter":58,"arphex:maggot_larvae":4,"alexsmobs:raccoon":15,"arphex:scorpioid_clone":3,"alexsmobs:seagull":1,"born_in_chaos_v1:thornshell_crab":6,"minecraft:zoglin":1,"arphex:butterfly_bewitcher_giant":2,"arphex:locust_landscourge":4,"eyesinthedarkness:eyes":1,"born_in_chaos_v1:pumpkinhead":1,"minecraft:horse":1,"born_in_chaos_v1:dire_hound_leader":7,"arphex:hornet_harbinger":5,"arphex:long_legs_fly":5,"undead_revamp2:thebidy":28,"alexsmobs:tusklin":5,"born_in_chaos_v1:barrel_zombie":35,"born_in_chaos_v1:spiritof_chaos":20,"alexsmobs:guster":5,"born_in_chaos_v1:bone_imp_minion":50,"undead_revamp2:the_moonflower":112,"born_in_chaos_v1:decrepit_skeleton":85,"born_in_chaos_v1:dark_vortex":37,"arphex:scorpion_striker":7,"arphex:fly_festerer":6,"minecraft:enderman":47,"born_in_chaos_v1:lifestealer_true_form":2,"undead_revamp2:thewolf":13,"born_in_chaos_v1:zombie_clown":21,"endofherobrine:silverfish":184,"graveyard:skeleton_creeper":76,"arphex:spider_funnel":1,"undead_revamp2:thesmoker":45,"born_in_chaos_v1:scarlet_persecutor":13,"minecraft:turtle":2,"alexsmobs:kangaroo":2,"minecraft:pig":16,"arphex:spider_jump":3,"born_in_chaos_v1:diamond_termite":21,"minecraft:strider":2,"alexsmobs:mantis_shrimp":1,"minecraft:creeper":507,"born_in_chaos_v1:dread_hound":80,"minecraft:stray":132,"undead_revamp2:theskeeper":6,"alexsmobs:fly":27,"apollyon:the_damned":2,"arphex:spider_snatcher":9,"minecraft:blaze":35,"alexsmobs:dropbear":1,"undead_revamp2:bigsucker":19,"arphex:millipede_marauder":4,"born_in_chaos_v1:missioner":2,"alexsmobs:tarantula_hawk":6,"alexsmobs:tiger":2,"graveyard:revenant":2,"born_in_chaos_v1:zombie_clown_not_despawn":1,"alexsmobs:rattlesnake":4,"alexsmobs:sugar_glider":2,"born_in_chaos_v1:maggot":391,"minecraft:phantom":7,"born_in_chaos_v1:baby_spider":59,"undead_revamp2:coppertar":10,"alexsmobs:soul_vulture":9,"alexsmobs:bison":5,"arphex:ant_arsonist_drone":2,"undead_revamp2:thehorrors":3,"undead_revamp2:sucker":110,"alexsmobs:flying_fish":12,"born_in_chaos_v1:fallen_chaos_knight":11,"born_in_chaos_v1:felsteed":1,"alexsmobs:skunk":3,"minecraft:bat":7,"born_in_chaos_v1:mother_spider":3,"born_in_chaos_v1:phantom_creeper_copy":28,"sons_of_sins:betrayed_guzzler":13,"alexsmobs:caiman":1,"born_in_chaos_v1:nightmare_stalker":9,"alexsmobs:crow":4,"arphex:dragonfly_dreadnought":1},"minecraft:picked_up":{"minecraft:smithing_table":1,"minecraft:stone_slab":1,"minecraft:lead":24,"biomesoplenty:orange_autumn_sapling":14,"minecraft:enchanted_book":17,"arphex:scorch_charge":2,"dropthemeat:raw_turtle":3,"minecraft:polished_deepslate":4,"minecraft:polished_blackstone_brick_stairs":8,"minecraft:string":531,"biomesoplenty:yellow_autumn_sapling":13,"minecraft:pufferfish":43,"minecraft:shroomlight":4,"minecraft:diamond_leggings":2,"alexsmobs:emu_feather":7,"biomesoplenty:redwood_wood":19,"dropthemeat:cooked_villager":3,"born_in_chaos_v1:shattered_skull":13,"minecraft:acacia_log":3,"minecraft:golden_axe":1,"minecraft:warped_button":1,"minecraft:golden_chestplate":3,"minecraft:yellow_banner":1,"minecraft:orange_bed":2,"minecraft:stone_sword":25,"arphex:bloodworm_grub":29,"minecraft:lime_carpet":1,"minecraft:honey_bottle":4,"farmersdelight:onion":4,"minecraft:polished_basalt":3,"minecraft:bookshelf":15,"minecraft:end_rod":2,"minecraft:blaze_rod":17,"dropthemeat:raw_dolphin":1,"minecraft:iron_bars":12,"minecraft:snowball":256,"biomesoplenty:lavender":51,"minecraft:feather":36,"minecraft:cooked_beef":25,"farmersdelight:rice":2,"minecraft:water_bucket":1,"minecraft:dark_oak_boat":10,"arphex:brown_scarab":3,"arphex:ectoplasm":29,"biomesoplenty:fir_sapling":31,"alexsmobs:bison_fur":4,"minecraft:flint":91,"alexsmobs:cooked_kangaroo_meat":14,"farmersdelight:tomato":25,"minecraft:dark_oak_sign":1,"minecraft:diamond_helmet":1,"arphex:spider_jar":1,"minecraft:honeycomb":1,"born_in_chaos_v1:mint_candy":12,"biomesoplenty:mahogany_planks":6,"born_in_chaos_v1:nightmare_mantleofthe_night_leggings":1,"minecraft:stripped_spruce_log":8,"arphex:infernal_boots":2,"minecraft:blue_terracotta":2,"minecraft:lever":4,"minecraft:granite":67,"alexsmobs:tarantula_hawk_wing_fragment":4,"minecraft:golden_horse_armor":1,"minecraft:jack_o_lantern":8,"born_in_chaos_v1:rotten_fish":292,"minecraft:light_gray_carpet":10,"arphex:locust_larvae":5,"minecraft:diamond_pickaxe":8,"minecraft:crimson_roots":9,"minecraft:mud":65,"minecraft:clay_ball":157,"born_in_chaos_v1:seedof_chaos":21,"minecraft:golden_pickaxe":2,"minecraft:leather_leggings":14,"born_in_chaos_v1:charmof_resistance":1,"backpacked:backpack":4,"biomesoplenty:jacaranda_sapling":7,"dropthemeat:raw_bee":7,"arphex:infernal_chestplate":3,"minecraft:flint_and_steel":5,"born_in_chaos_v1:intoxicating_decoction":11,"minecraft:white_carpet":1,"born_in_chaos_v1:smoked_fish":1,"minecraft:jungle_sapling":2,"minecraft:poppy":7,"minecraft:spruce_slab":50,"minecraft:birch_sapling":96,"minecraft:stone":6,"minecraft:fire_charge":4,"farmersdelight:tomato_seeds":24,"born_in_chaos_v1:pieceofdarkmetal":176,"dropthemeat:raw_wolf":5,"minecraft:diamond_chestplate":3,"minecraft:hay_block":18,"arphex:bane_of_the_darkness":1,"minecraft:cracked_deepslate_bricks":25,"born_in_chaos_v1:spiny_shell":26,"minecraft:oak_chest_boat":10,"minecraft:totem_of_undying":1,"minecraft:polished_blackstone":26,"minecraft:mutton":29,"minecraft:bone_block":6,"biomesoplenty:orange_sand":3,"born_in_chaos_v1:nightmare_mantleofthe_night_boots":1,"minecraft:mud_bricks":1,"minecraft:clock":1,"born_in_chaos_v1:monster_flesh":72,"minecraft:tripwire_hook":3,"arphex:crawling_compost_chunk":1,"minecraft:lily_pad":41,"alexsmobs:mosquito_proboscis":1,"minecraft:paper":50,"born_in_chaos_v1:soul_cutlass":2,"minecraft:light_blue_banner":2,"minecraft:apple":29,"horror_element_mod:bloody_tombstone":2,"alexsmobs:cockroach_wing_fragment":2,"born_in_chaos_v1:smoked_flesh":85,"minecraft:stone_pickaxe":5,"minecraft:iron_ore":4,"arphex:infernal_shard":4,"minecraft:gray_bed":3,"minecraft:dark_oak_stairs":10,"minecraft:smooth_basalt":37,"arphex:chitin":5,"minecraft:red_wool":5,"born_in_chaos_v1:orbofthe_summoner":3,"graveyard:skeleton_hand":2,"born_in_chaos_v1:fangofthe_hound_leader":2,"minecraft:crying_obsidian":13,"minecraft:leather_helmet":10,"biomesoplenty:mahogany_log":46,"farmersdelight:stuffed_potato":12,"minecraft:slime_ball":77,"born_in_chaos_v1:pile_of_skulls":1,"minecraft:birch_sign":4,"dropthemeat:raw_bat":7,"minecraft:lodestone":1,"minecraft:red_nether_brick_slab":1,"minecraft:baked_potato":3,"minecraft:hopper":17,"arphex:formic_fireblaster":1,"minecraft:gilded_blackstone":8,"minecraft:stone_brick_stairs":7,"born_in_chaos_v1:holiday_candy":57,"minecraft:lapis_block":3,"alexsmobs:gazelle_horn":2,"minecraft:dead_tube_coral_block":9,"minecraft:spruce_chest_boat":6,"horror_element_mod:blood_3":3,"minecraft:experience_bottle":13,"born_in_chaos_v1:chocolate_heart":10,"alexsmobs:dropbear_claw":2,"alexsmobs:blood_sac":13,"minecraft:red_sand":70,"minecraft:bucket":2,"comforts:sleeping_bag_white":128,"minecraft:red_dye":2,"born_in_chaos_v1:smoldering_infernal_ember":16,"minecraft:rose_bush":5,"minecraft:cobblestone_slab":13,"minecraft:ender_eye":21,"arphex:giant_spinneret":11,"born_in_chaos_v1:stimulating_decoction":9,"minecraft:iron_pickaxe":14,"alexsmobs:raccoon_tail":6,"dropthemeat:villager_nose":2,"minecraft:tipped_arrow":72,"minecraft:acacia_fence":3,"minecraft:spruce_stairs":34,"minecraft:diorite":150,"minecraft:rotten_flesh":1426,"biomesoplenty:mahogany_sapling":6,"dropthemeat:raw_iron_golem":1,"alexsmobs:emu_egg":1,"minecraft:mangrove_roots":17,"minecraft:deepslate_brick_stairs":1,"minecraft:obsidian":71,"minecraft:blaze_powder":3,"minecraft:cobblestone":3140,"minecraft:enchanting_table":1,"minecraft:muddy_mangrove_roots":58,"minecraft:leather_chestplate":10,"minecraft:lilac":3,"minecraft:andesite":42,"minecraft:black_bed":4,"minecraft:golden_leggings":2,"minecraft:beacon":1,"born_in_chaos_v1:mint_ice_cream":9,"minecraft:potato":50,"born_in_chaos_v1:staff_of_magic_arrows":4,"minecraft:smooth_sandstone_stairs":11,"minecraft:prismarine_bricks":6,"graveyard:dark_iron_door":6,"horror_element_mod:villager_head":4,"minecraft:dirt":1611,"minecraft:name_tag":6,"minecraft:bone":1035,"minecraft:bow":72,"minecraft:wheat_seeds":273,"minecraft:grindstone":1,"minecraft:mossy_stone_bricks":21,"minecraft:bamboo":154,"minecraft:prismarine":2,"minecraft:grass_block":96,"minecraft:diamond_block":2,"minecraft:spectral_arrow":74,"minecraft:mossy_cobblestone":16,"arphex:abyssal_annihilator":2,"minecraft:sugar":22,"minecraft:yellow_carpet":5,"minecraft:slime_block":2,"minecraft:soul_lantern":3,"minecraft:cracked_polished_blackstone_bricks":68,"alexsmobs:rattlesnake_rattle":8,"minecraft:crossbow":6,"minecraft:bone_meal":20,"minecraft:golden_apple":6,"graveyard:small_red_urn":1,"minecraft:spruce_sign":2,"minecraft:emerald":53,"minecraft:netherrack":10895,"born_in_chaos_v1:sea_terror_stomach":18,"minecraft:andesite_slab":4,"nethersdelight:hoglin_loin":25,"born_in_chaos_v1:diamond_termite_shard":33,"minecraft:azure_bluet":4,"undead_revamp2:chainsword":3,"minecraft:splash_potion":3,"born_in_chaos_v1:river_mint":1,"minecraft:ladder":7,"minecraft:brown_mushroom":161,"nethersdelight:propelpearl":3,"minecraft:stone_brick_wall":10,"biomesoplenty:huge_lily_pad":11,"minecraft:chain":18,"minecraft:shield":17,"minecraft:oak_trapdoor":1,"minecraft:moss_carpet":22,"vtaw_mw:diamond_battleaxe":1,"minecraft:birch_fence":4,"minecraft:blackstone":497,"alexsmobs:serrated_shark_tooth":1,"graveyard:corruption":82,"alexsmobs:elastic_tendon":2,"minecraft:note_block":1,"alexsmobs:leafcutter_anthill":1,"minecraft:polished_blackstone_bricks":145,"minecraft:cookie":4,"born_in_chaos_v1:charmof_endurance":2,"minecraft:stone_pressure_plate":12,"minecraft:purple_terracotta":1,"minecraft:weeping_vines":5,"minecraft:nether_bricks":4,"arphex:infernal_helmet":2,"minecraft:black_banner":2,"minecraft:skeleton_skull":3,"born_in_chaos_v1:corpse_maggot":251,"farmersdelight:rich_soil":10,"minecraft:basalt":131,"minecraft:golden_carrot":5,"minecraft:leather":98,"minecraft:crimson_fungus":2,"minecraft:chainmail_chestplate":2,"biomesoplenty:jacaranda_planks":11,"minecraft:gunpowder":117,"minecraft:orange_terracotta":3,"minecraft:cooked_mutton":4,"arphex:infernal_leggings":2,"minecraft:red_carpet":1,"born_in_chaos_v1:bagof_candy":1,"minecraft:rabbit_hide":2,"minecraft:iron_ingot":256,"born_in_chaos_v1:chipped_black_argillite_brick":3,"minecraft:cooked_chicken":10,"minecraft:prismarine_brick_slab":1,"minecraft:polished_andesite_slab":4,"dropthemeat:cooked_piglin_porkchop":36,"biomesoplenty:waterlily":9,"minecraft:black_candle":6,"dropthemeat:raw_villager":23,"minecraft:emerald_block":20,"horror_element_mod:blood_7":2,"minecraft:stone_brick_slab":14,"minecraft:quartz":225,"minecraft:dandelion":6,"minecraft:amethyst_shard":103,"minecraft:soul_torch":21,"minecraft:red_banner":1,"minecraft:dark_oak_chest_boat":5,"minecraft:spruce_door":4,"minecraft:cut_red_sandstone":3,"arphex:fly_appendage":44,"minecraft:pumpkin_seeds":9,"vtaw_mw:diamond_katana":1,"minecraft:chainmail_leggings":2,"minecraft:mossy_cobblestone_stairs":3,"minecraft:terracotta":3,"minecraft:damaged_anvil":3,"minecraft:dark_oak_wood":2,"minecraft:seagrass":2,"minecraft:iron_chestplate":9,"arphex:roach_nymph":21,"minecraft:chainmail_boots":1,"minecraft:flower_pot":1,"minecraft:anvil":11,"minecraft:prismarine_shard":13,"minecraft:diamond_sword":12,"graveyard:light_gray_urn":4,"minecraft:oak_stairs":14,"minecraft:wither_rose":18,"minecraft:birch_button":3,"minecraft:golden_shovel":3,"alexsmobs:bone_serpent_tooth":2,"minecraft:golden_sword":2,"minecraft:polished_deepslate_wall":8,"minecraft:amethyst_block":35,"farmersdelight:cutting_board":1,"born_in_chaos_v1:mesh_door":2,"minecraft:dark_oak_trapdoor":2,"minecraft:soul_soil":16,"minecraft:cooked_salmon":16,"biomesoplenty:tall_lavender":5,"biomesoplenty:umbran_boat":2,"minecraft:beetroot":2,"comforts:sleeping_bag_black":10,"minecraft:gold_nugget":2410,"minecraft:cobbled_deepslate":1462,"born_in_chaos_v1:charmof_power":1,"minecraft:spruce_planks":339,"minecraft:netherite_upgrade_smithing_template":2,"minecraft:enchanted_golden_apple":2,"minecraft:coal_block":11,"minecraft:mangrove_log":20,"minecraft:dark_oak_door":16,"minecraft:golden_helmet":5,"undead_revamp2:suckermemebrane":26,"arphex:ascendant_staff":3,"minecraft:composter":2,"born_in_chaos_v1:pileof_dark_metal":3,"born_in_chaos_v1:coffee_candy":24,"minecraft:cherry_log":3,"alexsmobs:centipede_leg":3,"minecraft:rabbit_foot":7,"undead_revamp2:cloogerribs":30,"minecraft:tropical_fish":21,"minecraft:salmon_bucket":1,"minecraft:iron_block":2,"minecraft:blackstone_stairs":1,"alexsmobs:flying_fish":21,"minecraft:birch_log":507,"minecraft:magma_block":219,"minecraft:mossy_cobblestone_slab":1,"born_in_chaos_v1:spiritual_dust":25,"minecraft:iron_door":7,"minecraft:birch_slab":9,"minecraft:jungle_log":18,"minecraft:jungle_wood":6,"minecraft:smoker":2,"biomesoplenty:fir_log":119,"arphex:venomous_appendage":22,"born_in_chaos_v1:nightmare_stalker_skull":1,"minecraft:chipped_anvil":6,"undead_revamp2:blacpetalblock":11,"minecraft:gray_terracotta":40,"minecraft:glowstone_dust":37,"minecraft:moss_block":15,"graveyard:fire_brazier":2,"minecraft:ink_sac":47,"minecraft:fermented_spider_eye":37,"minecraft:loom":2,"minecraft:dark_oak_log":148,"minecraft:barrel":15,"undead_revamp2:heavytooth":7,"minecraft:white_candle":11,"alexsmobs:kangaroo_hide":5,"dropthemeat:raw_goat":3,"alexsmobs:guster_eye":3,"minecraft:writable_book":2,"minecraft:dead_brain_coral_block":7,"minecraft:bread":94,"minecraft:chainmail_helmet":6,"alexsmobs:maggot":39,"arphex:mangled_fly_flesh":1,"minecraft:dark_oak_fence":17,"minecraft:crafting_table":13,"minecraft:coarse_dirt":49,"minecraft:nether_wart":32,"minecraft:red_bed":9,"alexsmobs:pigshoes":1,"minecraft:netherite_scrap":1,"minecraft:cracked_stone_bricks":6,"minecraft:cartography_table":2,"minecraft:deepslate_diamond_ore":3,"minecraft:beef":110,"born_in_chaos_v1:gnawed_bones":9,"minecraft:iron_nugget":95,"graveyard:leaning_skeleton":2,"minecraft:chest":11,"arphex:fire_opal":4,"minecraft:egg":271,"minecraft:sandstone":765,"minecraft:oak_door":25,"alexsmobs:straddlite":8,"minecraft:spruce_fence":30,"minecraft:carrot":81,"minecraft:redstone":896,"vtaw_mw:iron_katana":2,"minecraft:prismarine_crystals":16,"minecraft:blue_carpet":2,"minecraft:tnt":151,"minecraft:cooked_cod":6,"biomesoplenty:jacaranda_log":21,"minecraft:beetroot_seeds":5,"born_in_chaos_v1:wood_splitter_axe":2,"minecraft:diamond_boots":1,"undead_revamp2:the_somnolenceextract":2,"minecraft:gold_ingot":65,"minecraft:glow_berries":9,"minecraft:white_wool":158,"dropthemeat:cooked_bat":11,"minecraft:red_mushroom_block":1,"minecraft:filled_map":11,"graveyard:small_light_gray_urn":5,"minecraft:oak_log":227,"minecraft:ancient_debris":40,"minecraft:golden_boots":4,"minecraft:blue_bed":35,"minecraft:white_banner":22,"farmersdelight:organic_compost":4,"minecraft:birch_pressure_plate":4,"dropthemeat:piglin_porkchop":34,"farmersrespite:strong_green_tea":4,"minecraft:stone_bricks":82,"minecraft:kelp":22,"minecraft:cobweb":84,"minecraft:glass_bottle":14,"minecraft:mangrove_planks":3,"minecraft:iron_sword":10,"biomesoplenty:umbran_log":100,"minecraft:prismarine_brick_stairs":3,"minecraft:dark_oak_slab":11,"born_in_chaos_v1:ethereal_spirit":64,"graveyard:ossuary":1,"minecraft:gravel":456,"minecraft:birch_stairs":6,"minecraft:spruce_sapling":17,"minecraft:spruce_log":91,"biomesoplenty:maple_sapling":39,"minecraft:purple_bed":30,"minecraft:stone_axe":7,"undead_revamp2:beespheromones":1,"dixtas_armory:iron_katana":1,"minecraft:scute":3,"minecraft:gray_wool":7,"securitycraft:universal_block_modifier":1,"minecraft:melon_seeds":6,"arphex:mangled_spider_flesh":2,"minecraft:stripped_dark_oak_log":39,"minecraft:mangrove_propagule":5,"minecraft:ender_pearl":37,"minecraft:chiseled_deepslate":6,"biomesoplenty:burning_blossom":63,"minecraft:wheat":126,"minecraft:iron_trapdoor":2,"minecraft:turtle_egg":1,"minecraft:potion":9,"minecraft:nether_brick":16,"minecraft:raw_copper":74,"arphex:necrotic_fang":4,"born_in_chaos_v1:dark_upgrade":1,"minecraft:iron_leggings":10,"minecraft:netherite_ingot":2,"minecraft:armor_stand":4,"minecraft:oak_sign":3,"minecraft:sea_pickle":1,"minecraft:deepslate_tiles":8,"biomesoplenty:fir_planks":2,"alexsmobs:cooked_moose_ribs":22,"minecraft:calcite":23,"nethersdelight:hoglin_sirloin":17,"arphex:ant_nest":1,"farmersdelight:cabbage_seeds":4,"minecraft:iron_boots":8,"alexsmobs:leafcutter_ant_chamber":10,"minecraft:furnace":2,"minecraft:stick":276,"arphex:fire_opal_shard":1,"minecraft:oak_fence":6,"born_in_chaos_v1:phantom_powder":21,"minecraft:torch":359,"arphex:maggot_grub":11,"minecraft:porkchop":30,"minecraft:target":1,"minecraft:pointed_dripstone":123,"born_in_chaos_v1:nightmare_claw":5,"born_in_chaos_v1:damned_demomans_hat_helmet":4,"born_in_chaos_v1:sea_terror_eye":32,"alexsdelight:raw_bison":18,"biomesoplenty:orange_cosmos":4,"minecraft:cod":267,"undead_revamp2:arapholia":32,"minecraft:nautilus_shell":11,"minecraft:magma_cream":19,"alexsmobs:bear_fur":7,"minecraft:tuff":106,"undead_revamp2:huntereye":12,"minecraft:horn_coral":2,"minecraft:wither_skeleton_skull":5,"minecraft:lapis_lazuli":1114,"born_in_chaos_v1:monster_skin":56,"minecraft:leather_boots":11,"minecraft:raw_gold":238,"minecraft:cobbled_deepslate_slab":3,"minecraft:oak_planks":149,"minecraft:stone_hoe":1,"minecraft:mossy_stone_brick_stairs":7,"minecraft:ghast_tear":11,"minecraft:black_terracotta":12,"minecraft:cooked_porkchop":27,"minecraft:sand":1534,"graveyard:bone_dagger":5,"minecraft:oak_pressure_plate":1,"vtaw_mw:iron_longsword":1,"minecraft:birch_chest_boat":14,"minecraft:jungle_planks":26,"minecraft:dead_bush":1,"minecraft:cyan_bed":21,"minecraft:chiseled_sandstone":2,"undead_revamp2:acidsack":4,"sons_of_sins:flesh_of_demise":6,"minecraft:spruce_fence_gate":5,"born_in_chaos_v1:fire_dust":15,"minecraft:diamond":88,"decorative_blocks:birch_palisade":1,"minecraft:spruce_boat":16,"graveyard:cyan_urn":1,"horror_element_mod:trapped_leg":1,"minecraft:oak_sapling":63,"arphex:black_widow_bow":4,"minecraft:nether_star":1,"undead_revamp2:bostroxingot":10,"minecraft:fishing_rod":13,"minecraft:charcoal":17,"minecraft:cocoa_beans":37,"minecraft:allium":3,"minecraft:chicken":28,"minecraft:cooked_rabbit":1,"biomesoplenty:flesh":58,"minecraft:wooden_pickaxe":4,"alexsmobs:roadrunner_feather":1,"minecraft:gold_block":43,"minecraft:diamond_horse_armor":1,"minecraft:stone_stairs":8,"minecraft:orange_concrete":4,"minecraft:iron_axe":4,"minecraft:item_frame":2,"alexsdelight:cooked_bison":6,"minecraft:candle":19,"minecraft:andesite_stairs":1,"minecraft:oak_boat":5,"dropthemeat:raw_squid":39,"minecraft:observer":1,"minecraft:light_gray_wool":1,"minecraft:lectern":23,"minecraft:sugar_cane":111,"minecraft:spruce_trapdoor":13,"minecraft:phantom_membrane":2,"minecraft:dark_oak_sapling":13,"minecraft:raw_iron":1040,"minecraft:copper_ingot":28,"minecraft:bowl":1,"born_in_chaos_v1:pumpkinstaffa":3,"minecraft:stone_button":10,"alexsmobs:leafcutter_ant_pupa":3,"minecraft:iron_horse_armor":1,"alexsmobs:crocodile_scute":3,"minecraft:dark_oak_planks":157,"minecraft:arrow":535,"biomesoplenty:umbran_sapling":6,"minecraft:jungle_stairs":1,"minecraft:saddle":12,"arphex:hypnotic_hellblaster":2,"born_in_chaos_v1:fused_bone":17,"minecraft:cracked_deepslate_tiles":9,"minecraft:crimson_stem":14,"minecraft:glow_ink_sac":5,"minecraft:salmon":103,"horror_element_mod:atmosphere_block":1,"minecraft:cut_sandstone":17,"born_in_chaos_v1:shell_mace":1,"minecraft:birch_planks":115,"alexsmobs:cachalot_whale_tooth":5,"minecraft:mushroom_stew":4,"minecraft:nether_wart_block":52,"minecraft:cobblestone_stairs":6,"minecraft:deepslate_tile_slab":10,"minecraft:smooth_sandstone":69,"dropthemeat:cooked_fox":1,"minecraft:red_nether_brick_stairs":1,"born_in_chaos_v1:spider_mandible":4,"born_in_chaos_v1:intoxicating_dagger":2,"arphex:burning_glands":40,"born_in_chaos_v1:caramel_pepper":13,"minecraft:soul_sand":65,"minecraft:book":234,"minecraft:scaffolding":6,"minecraft:oak_slab":32,"minecraft:birch_boat":16,"minecraft:pumpkin":17,"born_in_chaos_v1:lifestealer_bone":4,"minecraft:raw_iron_block":2,"minecraft:dripstone_block":8,"biomesoplenty:dead_planks":5,"born_in_chaos_v1:nightmare_mantleofthe_night_chestplate":1,"born_in_chaos_v1:dark_rod":15,"biomesoplenty:porous_flesh":8,"minecraft:blast_furnace":3,"minecraft:white_bed":76,"minecraft:mossy_stone_brick_slab":7,"minecraft:spider_eye":85,"undead_revamp2:rawbostrox":19,"alexsmobs:raw_catfish":2,"biomesoplenty:bramble":219,"minecraft:iron_helmet":12,"arphex:abyssal_crystal":7,"minecraft:black_wool":3,"minecraft:coal":1082},"minecraft:broken":{"minecraft:diamond_helmet":1,"minecraft:iron_leggings":7,"minecraft:leather_helmet":1,"minecraft:wooden_pickaxe":3,"minecraft:shield":6,"undead_revamp2:acidsack":2,"minecraft:iron_pickaxe":2,"minecraft:stone_pickaxe":12,"minecraft:stone_axe":1,"vtaw_mw:iron_katana":1,"minecraft:stone_shovel":1,"minecraft:golden_boots":1,"minecraft:iron_boots":9,"minecraft:iron_chestplate":4,"minecraft:golden_sword":1,"minecraft:iron_sword":1,"minecraft:iron_axe":2,"minecraft:iron_helmet":11,"vtaw_mw:iron_longsword":1,"minecraft:wooden_axe":2,"minecraft:golden_pickaxe":1},"minecraft:mined":{"minecraft:red_nether_brick_slab":1,"minecraft:blue_carpet":3,"arphex:ant_nest":1,"minecraft:cut_sandstone_slab":1,"minecraft:blackstone_stairs":1,"minecraft:white_bed":72,"graveyard:small_black_urn":1,"graveyard:gray_urn":1,"alexsmobs:leafcutter_anthill":4,"minecraft:granite":44,"minecraft:acacia_log":3,"born_in_chaos_v1:dark_metal_deposit":13,"horror_element_mod:bloody_tombstone":1,"minecraft:light_gray_bed":2,"minecraft:oak_pressure_plate":1,"minecraft:nether_wart":6,"minecraft:spawner":95,"graveyard:wither_skull_with_rib_cage":2,"minecraft:polished_blackstone_bricks":199,"minecraft:magma_block":432,"biomesoplenty:tall_lavender":2,"minecraft:mossy_cobblestone_stairs":3,"minecraft:dark_oak_trapdoor":1,"minecraft:fire":1782,"minecraft:barrel":27,"minecraft:cobbled_deepslate":113,"minecraft:granite_slab":2,"minecraft:deepslate_lapis_ore":86,"minecraft:dead_tube_coral":2,"biomesoplenty:webbing":7,"horror_element_mod:sliced_body":1,"minecraft:player_head":1,"farmersdelight:rich_soil_farmland":1,"minecraft:tripwire":3,"minecraft:orange_bed":2,"minecraft:cut_sandstone":4,"graveyard:light_gray_urn":4,"minecraft:kelp_plant":5,"graveyard:dark_iron_trapdoor":1,"biomesoplenty:jacaranda_planks":17,"minecraft:crimson_nylium":5,"minecraft:smoker":1,"graveyard:fire_brazier":2,"minecraft:deepslate_tile_slab":11,"minecraft:powder_snow":398,"minecraft:torch":59,"minecraft:note_block":1,"minecraft:dark_oak_wood":2,"minecraft:white_stained_glass_pane":1,"minecraft:dead_bush":7,"farmersdelight:cabbages":3,"minecraft:white_candle":1,"minecraft:dead_tube_coral_fan":1,"minecraft:sugar_cane":56,"minecraft:bricks":6,"minecraft:amethyst_block":50,"minecraft:birch_sapling":3,"minecraft:chain":8,"minecraft:jungle_wood":2,"graveyard:wither_skeleton_hand":1,"minecraft:mud":83,"minecraft:wither_rose":9,"minecraft:grass":648,"minecraft:smooth_basalt":40,"minecraft:deepslate":926,"minecraft:suspicious_gravel":1,"minecraft:attached_pumpkin_stem":1,"minecraft:dark_prismarine":3,"biomesoplenty:orange_autumn_leaves":9,"minecraft:deepslate_tiles":59,"minecraft:mossy_cobblestone":21,"farmersdelight:wild_carrots":8,"minecraft:dark_oak_log":72,"minecraft:cyan_stained_glass":2,"minecraft:dark_oak_fence":19,"minecraft:spruce_fence":33,"graveyard:tg_deepslate":13,"minecraft:redstone_wire":16,"alexsmobs:leafcutter_ant_chamber":33,"minecraft:cartography_table":2,"horror_element_mod:broken_tv":2,"biomesoplenty:jacaranda_log":4,"minecraft:redstone_ore":18,"minecraft:andesite":42,"biomesoplenty:flesh":48,"minecraft:big_dripleaf_stem":1,"minecraft:mossy_stone_brick_stairs":11,"minecraft:vine":163,"minecraft:cobblestone_slab":12,"biomesoplenty:barley":27,"minecraft:bone_block":1,"minecraft:ender_chest":1,"biomesoplenty:porous_flesh":5,"minecraft:birch_stairs":6,"minecraft:oak_slab":34,"minecraft:redstone_block":1,"minecraft:glass_pane":6,"minecraft:soul_sand":20,"biomesoplenty:black_sand":5,"minecraft:dandelion":2,"graveyard:tg_rooted_dirt":2,"biomesoplenty:fir_planks":2,"horror_element_mod:hanging_corpse_1":3,"minecraft:copper_ore":21,"minecraft:tall_grass":93,"farmersdelight:wild_tomatoes":15,"minecraft:deepslate_gold_ore":119,"minecraft:diorite":152,"horror_element_mod:trapped_leg":1,"minecraft:coarse_dirt":38,"minecraft:mangrove_leaves":12,"minecraft:gravel":202,"minecraft:cobweb":275,"minecraft:polished_blackstone":34,"minecraft:stone_bricks":96,"minecraft:gold_ore":7,"minecraft:chipped_anvil":7,"minecraft:iron_trapdoor":2,"minecraft:fern":104,"undead_revamp2:arapholia":7,"minecraft:stone_pressure_plate":15,"minecraft:oak_sapling":24,"graveyard:tg_coarse_dirt":3,"farmersdelight:rich_soil":9,"minecraft:mossy_stone_brick_slab":5,"minecraft:andesite_stairs":1,"minecraft:spruce_trapdoor":6,"minecraft:dead_horn_coral":2,"minecraft:budding_amethyst":7,"arphex:crawling_compost":1,"minecraft:cracked_polished_blackstone_bricks":133,"minecraft:composter":2,"minecraft:gilded_blackstone":9,"minecraft:mossy_cobblestone_slab":1,"minecraft:sculk_catalyst":22,"farmersdelight:wild_rice":2,"minecraft:pointed_dripstone":40,"minecraft:flowering_azalea_leaves":1,"minecraft:iron_bars":17,"horror_element_mod:crucified_body":2,"minecraft:spruce_slab":47,"minecraft:gray_terracotta":55,"minecraft:deepslate_redstone_ore":143,"horror_element_mod:hazzmat_body":4,"minecraft:medium_amethyst_bud":2,"minecraft:orange_terracotta":2,"minecraft:jungle_stairs":1,"undead_revamp2:somnolencespawns":23,"minecraft:nether_quartz_ore":50,"minecraft:oak_planks":80,"minecraft:wall_torch":56,"minecraft:stone_stairs":9,"minecraft:warped_nylium":10,"biomesoplenty:huge_lily_pad":12,"minecraft:blue_terracotta":2,"minecraft:dark_oak_slab":9,"minecraft:blue_ice":7,"biomesoplenty:fir_log":20,"biomesoplenty:maple_leaves":8,"endofherobrine:glowstone":98,"minecraft:tnt":19,"graveyard:skull_pile":2,"minecraft:oak_log":179,"minecraft:dirt":537,"biomesoplenty:fir_sapling":1,"minecraft:ancient_debris":39,"minecraft:crying_obsidian":9,"minecraft:dark_oak_leaves":10,"minecraft:red_stained_glass":1,"minecraft:mangrove_roots":9,"minecraft:gray_glazed_terracotta":1,"born_in_chaos_v1:infected_diamond_ore":13,"horror_element_mod:hanging_villager":2,"minecraft:lever":2,"minecraft:glow_lichen":2,"minecraft:ladder":1,"minecraft:purple_terracotta":1,"minecraft:soul_campfire":1,"minecraft:birch_slab":10,"minecraft:spruce_leaves":35,"biomesoplenty:mahogany_sapling":2,"biomesoplenty:jacaranda_sapling":1,"minecraft:dead_horn_coral_wall_fan":1,"minecraft:crimson_stem":14,"horror_element_mod:herobrine_head":1,"minecraft:hay_block":18,"graveyard:small_light_blue_urn":1,"minecraft:light_blue_wall_banner":2,"minecraft:nether_sprouts":1,"minecraft:polished_basalt":6,"biomesoplenty:willow_vine":6,"minecraft:gold_block":53,"minecraft:bookshelf":61,"minecraft:deepslate_iron_ore":301,"minecraft:shroomlight":5,"biomesoplenty:flesh_tendons_strand":13,"born_in_chaos_v1:mesh_door":1,"minecraft:scaffolding":3,"minecraft:acacia_leaves":3,"minecraft:snow_block":5,"minecraft:stripped_dark_oak_log":49,"minecraft:basalt":119,"graveyard:small_light_gray_urn":12,"minecraft:oak_fence":4,"undead_revamp2:bostrokestone":4,"minecraft:lime_carpet":1,"minecraft:stone_slab":1,"graveyard:tg_grass_block":1,"minecraft:polished_blackstone_brick_stairs":4,"minecraft:prismarine_bricks":12,"minecraft:birch_planks":25,"graveyard:skull_with_rib_cage":3,"biomesoplenty:mahogany_log":5,"minecraft:ice":65,"minecraft:bee_nest":2,"minecraft:muddy_mangrove_roots":60,"minecraft:cocoa":7,"graveyard:leaning_skeleton":2,"minecraft:cracked_stone_bricks":11,"minecraft:mossy_stone_bricks":21,"biomesoplenty:redwood_wood":20,"minecraft:dark_oak_planks":86,"minecraft:black_terracotta":23,"minecraft:jungle_leaves":10,"minecraft:obsidian":57,"biomesoplenty:burning_blossom":78,"biomesoplenty:bramble":221,"minecraft:red_sand":19,"minecraft:stone_brick_wall":7,"minecraft:yellow_carpet":3,"minecraft:jungle_log":6,"biomesoplenty:eyebulb":5,"minecraft:coal_block":12,"minecraft:deepslate_bricks":1,"minecraft:deepslate_tile_stairs":6,"minecraft:hopper":17,"minecraft:crimson_fungus":2,"minecraft:orange_concrete":10,"horror_element_mod:rotten_body":3,"minecraft:weeping_vines_plant":6,"minecraft:tall_seagrass":4,"horror_element_mod:villager_head":5,"minecraft:sticky_piston":2,"biomesoplenty:lavender":32,"minecraft:pumpkin":18,"graveyard:ossuary":1,"minecraft:moss_carpet":1,"biomesoplenty:flesh_tendons":5,"endofherobrine:mossy_cobblestone":33,"minecraft:enchanting_table":2,"minecraft:sculk_shrieker":23,"minecraft:cave_vines":3,"minecraft:oak_sign":2,"minecraft:polished_deepslate_slab":14,"minecraft:dirt_path":28,"minecraft:oak_stairs":15,"minecraft:small_amethyst_bud":1,"minecraft:deepslate_brick_stairs":8,"minecraft:smooth_sandstone_stairs":6,"minecraft:iron_block":2,"horror_element_mod:spiked_body":2,"minecraft:soul_wall_torch":21,"minecraft:brown_mushroom":165,"minecraft:red_bed":9,"minecraft:soul_fire":88,"biomesoplenty:blackstone_spines":1,"minecraft:amethyst_cluster":22,"minecraft:blast_furnace":1,"arphex:scorch":5,"minecraft:glass":17,"minecraft:cyan_bed":23,"minecraft:damaged_anvil":3,"minecraft:skeleton_skull":4,"minecraft:wheat":61,"minecraft:lilac":3,"biomesoplenty:large_rose_quartz_bud":3,"minecraft:black_bed":4,"minecraft:stone_brick_stairs":10,"minecraft:prismarine_brick_stairs":7,"horror_element_mod:dead_cow":2,"minecraft:loom":2,"graveyard:cyan_urn":1,"born_in_chaos_v1:infernal_evil_pumpkin_s":3,"minecraft:cut_red_sandstone":1,"minecraft:red_mushroom_block":8,"minecraft:piston":1,"biomesoplenty:watergrass":39,"minecraft:light_gray_stained_glass_pane":2,"minecraft:dead_bubble_coral":2,"horror_element_mod:blood_3":2,"minecraft:jack_o_lantern":7,"minecraft:cobbled_deepslate_slab":12,"minecraft:allium":3,"minecraft:jungle_planks":18,"minecraft:crimson_roots":13,"minecraft:moss_block":20,"biomesoplenty:dead_grass":40,"minecraft:kelp":2,"horror_element_mod:atmosphere_block":1,"minecraft:jungle_sapling":1,"graveyard:tg_moss_block":2,"minecraft:snow":40,"minecraft:diamond_block":2,"horror_element_mod:scientist_body":6,"graveyard:sarcophagus":1,"minecraft:potatoes":4,"biomesoplenty:high_grass":1,"horror_element_mod:blood_7":1,"minecraft:bamboo":15,"minecraft:white_wool":14,"minecraft:cake":1,"minecraft:smithing_table":1,"minecraft:light_gray_carpet":8,"minecraft:stone_brick_slab":15,"minecraft:observer":2,"minecraft:smooth_sandstone":5,"horror_element_mod:broken_light":1,"minecraft:emerald_ore":2,"biomesoplenty:high_grass_plant":5,"minecraft:cracked_deepslate_bricks":35,"graveyard:small_red_urn":1,"minecraft:purple_bed":30,"graveyard:vase_block":21,"minecraft:prismarine_brick_slab":3,"minecraft:spruce_log":94,"minecraft:birch_leaves":92,"minecraft:red_wall_banner":1,"minecraft:mycelium":1,"horror_element_mod:hospital_bed":6,"minecraft:dripstone_block":4,"biomesoplenty:stringy_cobweb":5,"minecraft:spruce_fence_gate":5,"minecraft:large_amethyst_bud":1,"minecraft:spruce_planks":163,"minecraft:attached_melon_stem":2,"minecraft:cobbled_deepslate_stairs":1,"minecraft:jungle_slab":3,"minecraft:cobblestone_stairs":4,"minecraft:sculk_vein":27,"minecraft:cave_vines_plant":1,"minecraft:grass_block":503,"minecraft:dead_tube_coral_block":9,"graveyard:dark_iron_door":7,"minecraft:soul_soil":11,"biomesoplenty:pus_bubble":2,"born_in_chaos_v1:pile_of_skulls":1,"biomesoplenty:blackstone_bulb":11,"comforts:sleeping_bag_white":8,"biomesoplenty:bramble_leaves":38,"minecraft:raw_iron_block":2,"minecraft:glowstone":6,"minecraft:red_nether_brick_stairs":1,"biomesoplenty:orange_cosmos":4,"minecraft:iron_ore":333,"graveyard:leaning_wither_skeleton":3,"minecraft:anvil":9,"minecraft:dark_oak_stairs":10,"minecraft:birch_wall_sign":2,"graveyard:small_brown_urn":3,"graveyard:wither_skull_pile":1,"horror_element_mod:hazzmat_head":1,"horror_element_mod:dead_experiment":4,"minecraft:blackstone":160,"farmersdelight:organic_compost":4,"horror_element_mod:beheaded_body":2,"minecraft:polished_deepslate_stairs":5,"minecraft:soul_lantern":1,"minecraft:clay":21,"minecraft:calcite":37,"minecraft:potted_warped_roots":1,"minecraft:chest":8,"minecraft:mushroom_stem":21,"minecraft:cobblestone":156,"minecraft:slime_block":2,"minecraft:grindstone":1,"minecraft:prismarine":2,"minecraft:iron_door":6,"minecraft:seagrass":9,"minecraft:dark_oak_door":4,"minecraft:nether_wart_block":27,"farmersdelight:cutting_board":1,"minecraft:birch_log":494,"minecraft:lapis_block":3,"horror_element_mod:spiked_villager":2,"biomesoplenty:hair":1,"biomesoplenty:waterlily":7,"minecraft:cracked_deepslate_tiles":29,"biomesoplenty:clover":11,"minecraft:acacia_fence":3,"minecraft:waxed_oxidized_copper":1,"minecraft:sand":1674,"minecraft:wither_skeleton_skull":3,"horror_element_mod:colonial_marine_body":2,"minecraft:netherrack":4212,"minecraft:oak_leaves":115,"minecraft:polished_deepslate_wall":6,"minecraft:emerald_block":21,"minecraft:nether_gold_ore":351,"minecraft:diamond_ore":1,"minecraft:red_carpet":1,"minecraft:tuff":112,"farmersdelight:onions":3,"minecraft:candle":9,"minecraft:deepslate_diamond_ore":43,"minecraft:oak_door":16,"biomesoplenty:bush":2,"minecraft:polished_andesite_slab":4,"farmersdelight:tomatoes":9,"minecraft:sandstone":812,"minecraft:rooted_dirt":4,"minecraft:large_fern":8,"minecraft:oak_trapdoor":2,"minecraft:furnace":3,"minecraft:carrots":14,"minecraft:chiseled_sandstone":1,"minecraft:stripped_spruce_log":4,"minecraft:chiseled_deepslate":6,"minecraft:polished_deepslate":10,"minecraft:packed_ice":325,"minecraft:stone":2564,"biomesoplenty:spider_egg":4,"minecraft:redstone_wall_torch":1,"minecraft:podzol":52,"minecraft:red_wool":6,"biomesoplenty:orange_sand":8,"minecraft:brick_wall":1,"minecraft:spruce_door":3,"minecraft:crafting_table":8,"minecraft:cyan_stained_glass_pane":1,"minecraft:rose_bush":4,"minecraft:andesite_slab":4,"minecraft:sculk_sensor":39,"minecraft:lectern":21,"born_in_chaos_v1:chipped_black_argillite_brick":6,"biomesoplenty:sprout":148,"minecraft:lapis_ore":38,"minecraft:lily_pad":17,"minecraft:sculk":331,"minecraft:blue_bed":33,"minecraft:spruce_stairs":31,"biomesoplenty:yellow_autumn_leaves":24,"minecraft:gray_bed":1,"minecraft:dead_brain_coral_block":7,"minecraft:coal_ore":863,"horror_element_mod:hanging_corpse_2":1,"minecraft:end_rod":2,"minecraft:lodestone":1,"minecraft:terracotta":3,"minecraft:birch_fence":2},"minecraft:dropped":{"biomesoplenty:fir_log":1,"minecraft:iron_sword":4,"minecraft:porkchop":1,"minecraft:lapis_lazuli":59,"graveyard:cyan_urn":1,"arphex:infernal_chestplate":2,"dropthemeat:piglin_porkchop":6,"minecraft:glow_ink_sac":3,"born_in_chaos_v1:nightmare_mantleofthe_night_chestplate":1,"minecraft:glass_bottle":2,"minecraft:diamond":1,"minecraft:crafting_table":6,"minecraft:dark_oak_slab":7,"minecraft:weeping_vines":2,"minecraft:glow_berries":4,"arphex:mangled_scorpion_flesh":3,"minecraft:black_bed":4,"minecraft:cracked_stone_bricks":1,"born_in_chaos_v1:sea_terror_eye":2,"alexsmobs:flying_fish_boots":1,"graveyard:corruption":53,"born_in_chaos_v1:damned_demomans_hat_helmet":4,"minecraft:emerald":10,"minecraft:red_bed":1,"alexsmobs:roadrunner_feather":2,"minecraft:dark_oak_fence":16,"arphex:fire_opal":2,"minecraft:dark_oak_trapdoor":1,"alexsmobs:flying_fish":3,"minecraft:gold_nugget":36,"minecraft:writable_book":4,"born_in_chaos_v1:staff_of_magic_arrows":2,"minecraft:sand":841,"undead_revamp2:blacpetalblock":1,"minecraft:dark_oak_planks":35,"minecraft:fishing_rod":7,"minecraft:white_wool":19,"minecraft:dark_oak_door":11,"minecraft:stone_axe":10,"minecraft:ancient_debris":1,"minecraft:lever":1,"minecraft:cooked_chicken":4,"minecraft:iron_nugget":71,"minecraft:cobbled_deepslate":333,"minecraft:wheat":30,"minecraft:obsidian":9,"undead_revamp2:arapholia":17,"minecraft:stripped_dark_oak_log":12,"graveyard:dark_iron_ingot":4,"minecraft:rotten_flesh":334,"minecraft:oak_planks":73,"minecraft:glowstone_dust":4,"minecraft:golden_shovel":1,"minecraft:azure_bluet":2,"minecraft:rabbit_foot":8,"minecraft:red_mushroom_block":1,"alexsmobs:blood_sac":1,"minecraft:jungle_log":10,"horror_element_mod:blood_3":2,"minecraft:leather_boots":26,"minecraft:leather_leggings":11,"minecraft:beef":3,"graveyard:light_gray_urn":2,"vtaw_mw:iron_katana":3,"minecraft:stone_brick_stairs":6,"minecraft:acacia_fence":1,"biomesoplenty:tall_lavender":5,"minecraft:golden_boots":7,"biomesoplenty:dead_planks":10,"born_in_chaos_v1:shattered_skull":2,"minecraft:wheat_seeds":128,"minecraft:dripstone_block":8,"biomesoplenty:maple_sapling":35,"minecraft:salmon_bucket":3,"minecraft:book":41,"alexsmobs:rattlesnake_rattle":6,"arphex:mangled_spider_flesh":5,"minecraft:deepslate_tile_slab":10,"alexsmobs:raw_catfish":2,"minecraft:mushroom_stew":7,"minecraft:golden_apple":6,"minecraft:yellow_carpet":5,"biomesoplenty:jacaranda_log":64,"minecraft:cobweb":71,"minecraft:diamond_horse_armor":1,"born_in_chaos_v1:gnawed_bones":6,"minecraft:gray_wool":1,"minecraft:ink_sac":52,"arphex:mangled_fly_flesh":1,"minecraft:cooked_salmon":1,"minecraft:potion":4,"minecraft:oak_stairs":1,"minecraft:white_banner":14,"minecraft:red_dye":2,"minecraft:mud":1,"minecraft:chipped_anvil":4,"minecraft:chainmail_leggings":7,"minecraft:smooth_sandstone":59,"minecraft:blue_carpet":2,"minecraft:lily_pad":33,"minecraft:stone_brick_slab":6,"minecraft:snow_block":16,"biomesoplenty:waterlily":9,"minecraft:soul_soil":12,"minecraft:cocoa_beans":18,"minecraft:experience_bottle":22,"minecraft:orange_concrete":4,"minecraft:white_carpet":2,"minecraft:clay_ball":157,"minecraft:iron_boots":7,"horror_element_mod:blood_7":2,"minecraft:damaged_anvil":1,"minecraft:name_tag":2,"minecraft:oak_sign":1,"minecraft:suspicious_stew":5,"minecraft:blast_furnace":2,"born_in_chaos_v1:pumpkinstaffa":1,"minecraft:diamond_sword":9,"minecraft:sea_pickle":6,"minecraft:flower_pot":1,"minecraft:spruce_boat":3,"minecraft:spruce_trapdoor":4,"minecraft:spruce_planks":117,"minecraft:diamond_pickaxe":8,"minecraft:stone_pressure_plate":10,"minecraft:barrel":4,"minecraft:stone_bricks":38,"minecraft:bamboo":118,"minecraft:sandstone":585,"minecraft:red_sand":52,"minecraft:bow":85,"minecraft:magma_block":180,"arphex:fly_appendage":6,"horror_element_mod:bloody_tombstone":2,"minecraft:moss_block":6,"minecraft:candle":19,"minecraft:soul_sand":26,"minecraft:oak_log":78,"minecraft:loom":2,"minecraft:dark_oak_sapling":13,"minecraft:leather":41,"minecraft:red_wool":2,"minecraft:prismarine_brick_stairs":5,"minecraft:jungle_planks":28,"minecraft:iron_horse_armor":2,"minecraft:mangrove_planks":6,"dropthemeat:cooked_bat":9,"biomesoplenty:orange_cosmos":4,"minecraft:birch_slab":1,"farmersdelight:rice":6,"minecraft:cod":64,"minecraft:cobblestone_stairs":1,"minecraft:cracked_polished_blackstone_bricks":8,"graveyard:leaning_skeleton":1,"minecraft:dark_oak_log":70,"born_in_chaos_v1:monster_skin":19,"minecraft:mutton":2,"minecraft:snowball":107,"farmersdelight:onion":4,"minecraft:gold_ingot":153,"biomesoplenty:bramble":86,"minecraft:andesite_slab":3,"biomesoplenty:yellow_autumn_sapling":6,"born_in_chaos_v1:smoked_fish":2,"minecraft:smooth_sandstone_stairs":7,"minecraft:soul_lantern":3,"minecraft:pointed_dripstone":2,"minecraft:white_candle":4,"biomesoplenty:orange_autumn_sapling":2,"minecraft:mossy_stone_brick_slab":6,"minecraft:cooked_mutton":1,"minecraft:leather_chestplate":15,"minecraft:mangrove_log":14,"minecraft:beetroot_seeds":2,"minecraft:stone_brick_wall":6,"born_in_chaos_v1:diamond_termite_shard":9,"minecraft:birch_button":2,"minecraft:iron_bars":9,"biomesoplenty:flesh":41,"undead_revamp2:chainsword":2,"biomesoplenty:mahogany_log":35,"minecraft:bread":84,"biomesoplenty:jacaranda_sapling":7,"minecraft:golden_helmet":3,"graveyard:ossuary":1,"vtaw_mw:diamond_katana":2,"minecraft:golden_axe":1,"minecraft:mangrove_propagule":5,"minecraft:amethyst_block":2,"minecraft:jungle_wood":6,"minecraft:tropical_fish":12,"minecraft:spruce_fence_gate":2,"arphex:abyssal_annihilator":1,"minecraft:black_candle":4,"farmersdelight:golden_knife":2,"minecraft:mossy_cobblestone_slab":1,"minecraft:nether_wart_block":17,"farmersdelight:organic_compost":4,"born_in_chaos_v1:fused_bone":2,"minecraft:iron_door":5,"minecraft:fire_charge":4,"minecraft:orange_bed":1,"born_in_chaos_v1:shell_mace":1,"born_in_chaos_v1:nightmare_mantleofthe_night_boots":1,"minecraft:tripwire_hook":1,"minecraft:polished_deepslate":3,"minecraft:kelp":14,"vtaw_mw:diamond_battleaxe":1,"minecraft:oak_trapdoor":1,"alexsmobs:tarantula_hawk_wing_fragment":1,"farmersdelight:cabbage_seeds":8,"minecraft:birch_pressure_plate":2,"arphex:formic_fireblaster":2,"graveyard:skeleton_hand":2,"arphex:hypnotic_hellblaster":2,"dixtas_armory:diamond_battle_axe":1,"minecraft:flint_and_steel":6,"minecraft:gray_terracotta":40,"minecraft:mud_bricks":1,"biomesoplenty:fir_planks":2,"minecraft:andesite":11,"born_in_chaos_v1:spiny_shell":2,"minecraft:golden_leggings":4,"born_in_chaos_v1:intoxicating_dagger":2,"minecraft:oak_sapling":47,"minecraft:birch_sign":1,"minecraft:wooden_pickaxe":2,"minecraft:magma_cream":3,"minecraft:nautilus_shell":1,"dropthemeat:cooked_villager":1,"minecraft:oak_pressure_plate":1,"minecraft:cooked_beef":1,"minecraft:crossbow":6,"arphex:infernal_shard":4,"born_in_chaos_v1:sea_terror_stomach":1,"biomesoplenty:mahogany_planks":26,"minecraft:mossy_stone_brick_stairs":6,"arphex:black_widow_bow":8,"minecraft:saddle":3,"arphex:infernal_helmet":2,"minecraft:leather_helmet":6,"minecraft:red_carpet":1,"minecraft:item_frame":1,"minecraft:dirt":869,"born_in_chaos_v1:monster_flesh":26,"arphex:bloodworm_grub":3,"born_in_chaos_v1:phantom_powder":4,"minecraft:stone_button":10,"minecraft:cracked_deepslate_tiles":4,"backpacked:backpack":4,"minecraft:jack_o_lantern":3,"minecraft:horn_coral":1,"minecraft:chain":8,"minecraft:jungle_sapling":2,"minecraft:bone_block":3,"minecraft:wooden_sword":1,"arphex:giant_spinneret":1,"born_in_chaos_v1:trident_hayfork":1,"minecraft:bone_meal":15,"minecraft:sugar":1,"minecraft:iron_pickaxe":9,"dropthemeat:raw_bee":2,"minecraft:dark_oak_boat":1,"alexsmobs:raccoon_tail":1,"minecraft:blue_bed":3,"minecraft:bone":314,"minecraft:oak_door":4,"minecraft:emerald_block":26,"minecraft:golden_chestplate":6,"minecraft:nether_brick":6,"minecraft:birch_sapling":4,"minecraft:blue_wool":8,"born_in_chaos_v1:smoked_flesh":90,"minecraft:light_gray_carpet":10,"minecraft:white_bed":3,"alexsmobs:cachalot_whale_tooth":1,"minecraft:salmon":5,"minecraft:chiseled_deepslate":2,"dixtas_armory:iron_katana":1,"minecraft:deepslate_tiles":8,"minecraft:jungle_stairs":1,"minecraft:charcoal":26,"minecraft:ladder":3,"minecraft:yellow_banner":2,"farmersdelight:rope":11,"arphex:spider_jar":3,"minecraft:spruce_slab":28,"minecraft:crying_obsidian":8,"minecraft:lectern":1,"minecraft:enchanted_book":11,"minecraft:egg":8,"dropthemeat:raw_bat":5,"farmersdelight:tomato_seeds":21,"minecraft:crimson_planks":19,"arphex:bane_of_the_darkness":3,"minecraft:iron_ingot":173,"born_in_chaos_v1:intoxicating_decoction":4,"minecraft:tnt":2,"minecraft:polished_blackstone":2,"minecraft:oak_fence":7,"biomesoplenty:lavender":44,"minecraft:feather":7,"minecraft:cobblestone":528,"minecraft:iron_helmet":11,"minecraft:apple":1,"minecraft:granite":39,"biomesoplenty:jacaranda_planks":43,"minecraft:spruce_door":1,"born_in_chaos_v1:soul_cutlass":1,"graveyard:bone_dagger":4,"minecraft:chainmail_helmet":4,"minecraft:coal":311,"minecraft:pufferfish":4,"arphex:infernal_boots":2,"minecraft:iron_trapdoor":2,"minecraft:golden_carrot":4,"minecraft:wooden_hoe":1,"alexsmobs:leafcutter_ant_chamber":9,"minecraft:rose_bush":3,"minecraft:gray_bed":2,"minecraft:lime_carpet":1,"minecraft:diamond_helmet":1,"minecraft:dead_bush":1,"minecraft:heart_of_the_sea":1,"minecraft:mossy_cobblestone_stairs":2,"minecraft:iron_shovel":3,"minecraft:paper":36,"minecraft:string":139,"minecraft:polished_deepslate_wall":8,"minecraft:spruce_sapling":17,"minecraft:moss_carpet":18,"minecraft:netherite_ingot":2,"minecraft:stone_sword":22,"minecraft:dark_oak_sign":1,"born_in_chaos_v1:rotten_fish":22,"minecraft:chicken":1,"minecraft:stone_slab":1,"minecraft:nether_bricks":4,"minecraft:spruce_fence":14,"minecraft:pumpkin_seeds":7,"arphex:roach_nymph":1,"minecraft:target":1,"minecraft:potato":10,"minecraft:cobblestone_slab":3,"minecraft:hay_block":10,"minecraft:stone":6,"dropthemeat:raw_squid":32,"minecraft:allium":3,"dixtas_armory:diamond_longsword":1,"minecraft:wooden_shovel":4,"minecraft:spider_eye":47,"minecraft:warped_button":1,"minecraft:birch_boat":6,"farmersdelight:tomato":7,"minecraft:spruce_sign":2,"minecraft:brown_mushroom":1,"minecraft:birch_planks":97,"minecraft:dark_oak_stairs":2,"graveyard:small_red_urn":1,"minecraft:red_nether_brick_slab":1,"minecraft:netherite_upgrade_smithing_template":2,"minecraft:scute":2,"biomesoplenty:porous_flesh":8,"minecraft:flint":8,"alexsdelight:cooked_bison":6,"minecraft:polished_blackstone_brick_stairs":6,"minecraft:crimson_roots":7,"minecraft:seagrass":2,"minecraft:cooked_cod":49,"minecraft:cut_sandstone":12,"born_in_chaos_v1:bagof_candy":1,"minecraft:amethyst_shard":20,"minecraft:polished_blackstone_bricks":29,"minecraft:birch_log":7,"biomesoplenty:burning_blossom":30,"minecraft:armor_stand":2,"minecraft:gravel":177,"minecraft:crimson_fungus":3,"minecraft:blackstone":446,"undead_revamp2:suckermemebrane":10,"minecraft:mangrove_roots":17,"born_in_chaos_v1:ethereal_spirit":5,"minecraft:black_terracotta":9,"minecraft:fern":4,"minecraft:diamond_shovel":2,"minecraft:stone_stairs":2,"minecraft:chainmail_chestplate":12,"minecraft:poppy":5,"born_in_chaos_v1:chipped_black_argillite_brick":3,"minecraft:skeleton_skull":1,"minecraft:gunpowder":45,"dropthemeat:raw_goat":3,"minecraft:melon_seeds":5,"born_in_chaos_v1:corpse_maggot":78,"minecraft:chest":2,"minecraft:chainmail_boots":5,"comforts:sleeping_bag_white":10,"minecraft:arrow":51,"minecraft:basalt":62,"minecraft:prismarine_bricks":3,"born_in_chaos_v1:nightmare_mantleofthe_night_leggings":1,"minecraft:quartz":40,"minecraft:netherrack":8042,"born_in_chaos_v1:dark_rod":3,"minecraft:spruce_chest_boat":1,"minecraft:water_bucket":1,"minecraft:oak_slab":1,"born_in_chaos_v1:wood_splitter_axe":1,"minecraft:mossy_cobblestone":5,"minecraft:bookshelf":15,"minecraft:diamond_leggings":2,"minecraft:lead":1,"minecraft:copper_ingot":16,"minecraft:grass_block":67,"vtaw_mw:iron_longsword":1,"minecraft:stick":79,"arphex:abyssal_crystal":3,"biomesoplenty:orange_sand":2,"minecraft:deepslate_brick_stairs":1,"minecraft:diorite":14,"born_in_chaos_v1:river_mint":1,"minecraft:torch":217,"biomesoplenty:huge_lily_pad":11,"minecraft:iron_leggings":9,"minecraft:wither_rose":9,"minecraft:iron_axe":2,"farmersdelight:rich_soil":3,"minecraft:bucket":1,"minecraft:dandelion":5,"minecraft:redstone":189,"graveyard:dark_iron_door":3,"nethersdelight:hoglin_sirloin":3,"alexsmobs:maggot":24,"minecraft:coarse_dirt":16,"minecraft:blaze_rod":6,"minecraft:nether_wart":16,"minecraft:raw_copper":11,"minecraft:tuff":25,"minecraft:composter":2,"minecraft:raw_iron":30,"minecraft:wither_skeleton_skull":3,"minecraft:smoker":1,"minecraft:cut_red_sandstone":3,"arphex:infernal_leggings":2,"minecraft:filled_map":24,"securitycraft:universal_block_remover":2,"graveyard:small_light_gray_urn":5,"minecraft:shield":7,"minecraft:diamond_chestplate":3,"minecraft:orange_terracotta":3,"minecraft:iron_chestplate":12,"arphex:ascendant_staff":2,"minecraft:mossy_stone_bricks":11,"minecraft:purple_bed":2,"minecraft:oak_boat":4,"minecraft:golden_sword":5,"minecraft:slime_ball":9,"minecraft:beacon":1,"minecraft:stone_pickaxe":11,"minecraft:raw_gold":14,"minecraft:cracked_deepslate_bricks":23,"born_in_chaos_v1:bone_heart":1}},"DataVersion":3465}